glaciersat/__init__.py
glaciersat/cfg.py
glaciersat/params.cfg
glaciersat/utils.py
glaciersat/version.py
glaciersat/core/__init__.py
glaciersat/core/albedo.py
glaciersat/core/gis.py
glaciersat/core/imagery.py
glaciersat/core/snowlines.py
glaciersat/operational/cronjobs.py
glaciersat/tests/__init__.py
glaciersat/tests/test_albedo.py
glaciersat/tests/test_utils.py
glaciersat-0.0.1a0.dist-info/LICENSE
glaciersat-0.0.1a0.dist-info/METADATA
glaciersat-0.0.1a0.dist-info/WHEEL
glaciersat-0.0.1a0.dist-info/top_level.txt
glaciersat-0.0.1a0.dist-info/RECORD
