Metadata-Version: 2.1
Name: glaciersat
Version: 0.0.1a0
Summary: glaciersat - monitoring glaciers from space
Home-page: https://github.com/jlandmann/glaciersat
Author: Johannes Marian Landmann
Author-email: landmann@vaw.baug.ethz.ch
License: MIT
Keywords: geosciences,glaciers,remote sensing,gis
Classifier: Development Status :: 3 - Alpha
Classifier: Intended Audience :: Science/Research
Classifier: License :: OSI Approved :: MIT License
Classifier: Programming Language :: Python :: 3.9
Requires-Python: >=3.6
License-File: LICENSE
Requires-Dist: numpy
Requires-Dist: scipy
Requires-Dist: pandas
Requires-Dist: matplotlib (>=3.0.0)
Requires-Dist: shapely
Requires-Dist: configobj
Requires-Dist: netcdf4
Requires-Dist: xarray (>=0.16)
Requires-Dist: sentinelsat
Requires-Dist: salem
